{
  "mshs": "1400191231",
  "msnv": "052078",
  "hoten": "Sâm Thị Lưu Ly",
  "ngaysinh": "07/09/1982",
  "diachi": "Xóm Khục - X. Châu Lộc - Nghệ An",
  "dantoc": "Thái",
  "sothebhyt": "DN4747412074929",
  "cccd": "",
  "ngayvv": "28/07/2025",
  "ngayrv": "03/08/2025",
  "chandoanvv": "U xơ tử cung loại 2 (D25), Cường kinh (N92.0), Thiếu máu (D53)",
  "chandoanrv": "Hậu phẫu nội soi bóc u xơ tử cung ngày 5/ U xơ tử cung loại 2 (D25), cường kinh (N92.0), thiếu máu (D53)",
  "benhsu": "Kinh cuối 05/07/2025. Rong kinh lượng nhiều kéo dài gây mệt. Khám trước đó ghi nhận u xơ tử cung loại 2, thiếu máu. Nhập viện vì rong kinh kéo dài, điều trị ngoại khoa.",
  "tiensu": "PARA 1-0-0-1. Chưa ghi nhận phẫu thuật. Không bệnh nội khoa đáng kể. Không dị ứng thuốc hay thức ăn.",
  "thamkham": "Da niêm hồng; bụng mềm. Khám phụ khoa: âm đạo không huyết, cổ tử cung láng; tử cung tương đương thai 12 tuần; phần phụ mềm.",
  "canlamsang": "Siêu âm: TC ngả trước; nội mạc 13 mm; u xơ thành trước ~57×48×49 mm, tưới máu độ 2; CTC bình thường; hai BT bình thường; không dịch ổ bụng.",
  "noihayngoaikhoa": "Ngoại khoa",
  "phuongphapdieutri": "Phẫu thuật nội soi bóc u xơ tử cung; may phục hồi cơ tử cung bằng Vicryl 1/0; rửa sạch ổ bụng; gửi GPB; mất máu ~100 ml.",
  "phuongphapvocam": "Mê nội khí quản",
  "giaiphaubenh": "U cơ trơn lành (leiomyoma).",
  "tinhtrangravien": "Đỡ",
  "huongdieutri": "Tái khám theo hẹn, dùng thuốc đúng toa."
  }